setup.py
RigolDG5000/RigolDG5000.py
RigolDG5000/VISA_wrapper_metaclass.py
RigolDG5000/VisaList.py
RigolDG5000/__init__.py
RigolDG5000.egg-info/PKG-INFO
RigolDG5000.egg-info/SOURCES.txt
RigolDG5000.egg-info/dependency_links.txt
RigolDG5000.egg-info/top_level.txt