Metadata-Version: 1.1
Name: RigolDG5000
Version: 0.2
Summary: Interface to the Rigol DG5000 waveform generator
Home-page: UNKNOWN
Author: Pierre Cladé
Author-email: pierre.clade@spectro.jussieu.fr
License: This software can be used under one of the following two licenses: (1) The BSD license. (2) Any other license, as long as it is obtained from the original author.
Keywords: Rigol,DG5000
Platform: UNKNOWN
Classifier: Development Status :: 4 - Beta
Classifier: Intended Audience :: Developers
Classifier: Intended Audience :: Education
Classifier: Intended Audience :: Other Audience
Classifier: Intended Audience :: Science/Research
Classifier: License :: OSI Approved :: BSD License
Classifier: Programming Language :: Python
Classifier: Topic :: Scientific/Engineering
Classifier: Topic :: Scientific/Engineering :: Physics
Classifier: Topic :: Software Development
Classifier: Topic :: Software Development :: Libraries
Classifier: Topic :: Software Development :: Libraries :: Python Modules
Requires: pyvisa
